sonyk_sdk/__init__.py
sonyk_sdk/agents/__init__.py
sonyk_sdk/agents/client.py
sonyk_sdk/agents/raw_client.py
sonyk_sdk/assets/__init__.py
sonyk_sdk/assets/client.py
sonyk_sdk/assets/raw_client.py
sonyk_sdk/assets/types/__init__.py
sonyk_sdk/assets/types/create_agent_text_asset_response.py
sonyk_sdk/assets/types/create_agent_text_asset_response_data.py
sonyk_sdk/assets/types/create_agent_text_asset_response_data_processing_info.py
sonyk_sdk/assets/types/delete_agent_asset_response.py
sonyk_sdk/assets/types/delete_agent_asset_response_data.py
sonyk_sdk/assets/types/get_agent_asset_content_response.py
sonyk_sdk/assets/types/get_agent_asset_content_response_data.py
sonyk_sdk/assets/types/get_agent_asset_content_response_data_type.py
sonyk_sdk/assets/types/list_agent_assets_request_type.py
sonyk_sdk/assets/types/search_agent_assets_request_type.py
sonyk_sdk/assets/types/search_agent_assets_response.py
sonyk_sdk/assets/types/search_agent_assets_response_data.py
sonyk_sdk/assets/types/search_agent_assets_response_data_results_item.py
sonyk_sdk/assets/types/search_agent_assets_response_data_results_item_asset_type.py
sonyk_sdk/assets/types/search_agent_assets_response_data_results_item_chunk_type.py
sonyk_sdk/assets/types/search_agent_assets_response_data_search_config.py
sonyk_sdk/assets/types/update_agent_asset_response.py
sonyk_sdk/assets/types/update_agent_asset_response_data.py
sonyk_sdk/assets/types/upload_agent_asset_response.py
sonyk_sdk/assets/types/upload_agent_asset_response_data.py
sonyk_sdk/assets/types/upload_agent_asset_response_data_processing_info.py
sonyk_sdk/calls/__init__.py
sonyk_sdk/calls/client.py
sonyk_sdk/calls/raw_client.py
sonyk_sdk/client.py
sonyk_sdk/core/__init__.py
sonyk_sdk/core/api_error.py
sonyk_sdk/core/client_wrapper.py
sonyk_sdk/core/datetime_utils.py
sonyk_sdk/core/file.py
sonyk_sdk/core/force_multipart.py
sonyk_sdk/core/http_client.py
sonyk_sdk/core/http_response.py
sonyk_sdk/core/jsonable_encoder.py
sonyk_sdk-0.9.5.dist-info/METADATA
sonyk_sdk-0.9.5.dist-info/WHEEL
sonyk_sdk-0.9.5.dist-info/RECORD
